CHANGES.rst
COPYING.txt
MANIFEST.in
README.rst
setup.cfg
setup.py
rattail_fabric2/__init__.py
rattail_fabric2/_version.py
rattail_fabric2/apache.py
rattail_fabric2/apt.py
rattail_fabric2/backup.py
rattail_fabric2/borg.py
rattail_fabric2/byjove.py
rattail_fabric2/certbot.py
rattail_fabric2/collectd.py
rattail_fabric2/composer.py
rattail_fabric2/core.py
rattail_fabric2/corepos.py
rattail_fabric2/docker.py
rattail_fabric2/ejabberd.py
rattail_fabric2/freetds.py
rattail_fabric2/luigi.py
rattail_fabric2/mariadb.py
rattail_fabric2/mssql.py
rattail_fabric2/mysql.py
rattail_fabric2/nodejs.py
rattail_fabric2/pod.py
rattail_fabric2/postfix.py
rattail_fabric2/postgresql.py
rattail_fabric2/python.py
rattail_fabric2/rattail.py
rattail_fabric2/soffice.py
rattail_fabric2/ssh.py
rattail_fabric2/util.py
rattail_fabric2.egg-info/PKG-INFO
rattail_fabric2.egg-info/SOURCES.txt
rattail_fabric2.egg-info/dependency_links.txt
rattail_fabric2.egg-info/not-zip-safe
rattail_fabric2.egg-info/requires.txt
rattail_fabric2.egg-info/top_level.txt
rattail_fabric2/deploy/check-rattail-daemon
rattail_fabric2/deploy/check-supervisor-process
rattail_fabric2/deploy/check-systemd-service
rattail_fabric2/deploy/soffice
rattail_fabric2/deploy/apt/listchanges.conf
rattail_fabric2/deploy/backup/backup-everything.mako
rattail_fabric2/deploy/backup/crontab.mako
rattail_fabric2/deploy/backup/git-exclude
rattail_fabric2/deploy/backup/logrotate.conf
rattail_fabric2/deploy/backup/luigi-logging.conf.mako
rattail_fabric2/deploy/backup/luigi-overnight.py
rattail_fabric2/deploy/backup/luigi.cfg.mako
rattail_fabric2/deploy/backup/overnight-backups.sh.mako
rattail_fabric2/deploy/backup/rattail-backup.mako
rattail_fabric2/deploy/backup/restart-overnight-backups.sh.mako
rattail_fabric2/deploy/backup/supervisor.conf.mako
rattail_fabric2/deploy/backup/upgrade.sh.mako
rattail_fabric2/deploy/collectd/check-mountpoints.py
rattail_fabric2/deploy/composer/install-composer.sh
rattail_fabric2/deploy/corepos/fannie-config.php.mako
rattail_fabric2/deploy/luigi/cron-overnight.sh.mako
rattail_fabric2/deploy/luigi/crontab.mako
rattail_fabric2/deploy/luigi/logging.conf.mako
rattail_fabric2/deploy/luigi/luigi-logrotate.conf.mako
