Metadata-Version: 2.1
Name: rattail-fabric2
Version: 0.3.3
Summary: Fabric (v2) Utilities for Rattail
Home-page: https://rattailproject.org/
Author: Lance Edgar
Author-email: lance@edbob.org
License: GNU GPL v3
Classifier: Development Status :: 3 - Alpha
Classifier: Environment :: Console
Classifier: Intended Audience :: Developers
Classifier: License :: OSI Approved :: GNU General Public License v3 or later (GPLv3+)
Classifier: Natural Language :: English
Classifier: Operating System :: OS Independent
Classifier: Programming Language :: Python :: 3
Classifier: Programming Language :: Python :: 3.5
Classifier: Topic :: System :: Systems Administration
Classifier: Topic :: Software Development :: Libraries :: Python Modules
License-File: COPYING.txt
Requires-Dist: fabric2
Requires-Dist: invoke
Requires-Dist: rattail
Requires-Dist: six
